mulberry/backends/__init__.py
mulberry/backends/numpy_backend.py
mulberry-0.1.1.dist-info/LICENSE
mulberry-0.1.1.dist-info/METADATA
mulberry-0.1.1.dist-info/WHEEL
mulberry-0.1.1.dist-info/top_level.txt
mulberry-0.1.1.dist-info/RECORD
