Metadata-Version: 2.1
Name: mulberry
Version: 0.1.1
Summary: Coordinate transformation tree with a focus on efficiency
Home-page: https://github.com/hdamron17/mulberry
Author: Hunter Damron
Author-email: hdamron1594@yahoo.com
License: UNKNOWN
Platform: UNKNOWN
Classifier: Development Status :: 1 - Planning
Classifier: Programming Language :: Python :: 3
Classifier: License :: OSI Approved :: BSD License
Classifier: Operating System :: OS Independent
Classifier: Topic :: Scientific/Engineering
Requires-Python: >=3.6
Requires-Dist: numpy
